gradoptics/__init__.py
gradoptics/distributions/__init__.py
gradoptics/distributions/atom_cloud.py
gradoptics/distributions/base_distribution.py
gradoptics/distributions/gaussian_distribution.py
gradoptics/inference/__init__.py
gradoptics/inference/rejection_sampling.py
gradoptics/integrator/__init__.py
gradoptics/integrator/base_integrator.py
gradoptics/integrator/stratified_sampling_integrator.py
gradoptics/light_sources/__init__.py
gradoptics/light_sources/base_light_source.py
gradoptics/light_sources/light_source_from_distribution.py
gradoptics/optics/__init__.py
gradoptics/optics/base_optics.py
gradoptics/optics/bounding_box.py
gradoptics/optics/bounding_shape.py
gradoptics/optics/bounding_sphere.py
gradoptics/optics/camera.py
gradoptics/optics/lens.py
gradoptics/optics/mirror.py
gradoptics/optics/psf.py
gradoptics/optics/ray.py
gradoptics/optics/sensor.py
gradoptics/optics/vector.py
gradoptics/optics/window.py
gradoptics/ray_tracing/__init__.py
gradoptics/ray_tracing/ray_tracing.py
gradoptics/ray_tracing/scene.py
gradoptics/transforms/__init__.py
gradoptics/transforms/base_transform.py
gradoptics/transforms/look_at_transform.py
gradoptics/transforms/simple_transform.py
gradoptics-0.0.2.dist-info/METADATA
gradoptics-0.0.2.dist-info/WHEEL
gradoptics-0.0.2.dist-info/licenses/LICENSE
gradoptics-0.0.2.dist-info/RECORD
