Metadata-Version: 2.1
Name: gradoptics
Version: 0.0.2
Summary: Differentiable Optics via Ray Tracing
Project-URL: Homepage, https://github.com/magis-slac/gradoptics
Project-URL: Bug Tracker, https://github.com/pypa/magis-slac/gradoptics
Author-email: Sean Gasiorowski <sgaz@slac.stanford.edu>, Michael Kagan <makagan@slac.stanford.edu>, Maxime Vandegar <maxime.vandegar@slac.stanford.edu>
License: MIT License
License-File: LICENSE
Classifier: License :: OSI Approved :: MIT License
Classifier: Operating System :: OS Independent
Classifier: Programming Language :: Python :: 3
Requires-Python: >=3.6
